tinyshar/__init__.py
tinyshar/_cli.py
tinyshar-0.10.3.dist-info/AUTHORS
tinyshar-0.10.3.dist-info/LICENSE
tinyshar-0.10.3.dist-info/METADATA
tinyshar-0.10.3.dist-info/WHEEL
tinyshar-0.10.3.dist-info/entry_points.txt
tinyshar-0.10.3.dist-info/top_level.txt
tinyshar-0.10.3.dist-info/RECORD
