Metadata-Version: 2.1
Name: tinyshar
Version: 0.10.3
Summary: simple library and utility for creation of shell archives
Home-page: https://github.com/kshpytsya/tinyshar
Author: Kyrylo Shpytsya
Author-email: kshpitsa@gmail.com
License: MIT
Classifier: Development Status :: 4 - Beta
Classifier: Intended Audience :: Developers
Classifier: Intended Audience :: Information Technology
Classifier: License :: OSI Approved :: MIT License
Classifier: Operating System :: POSIX
Classifier: Programming Language :: Python :: 3
Classifier: Topic :: System :: Installation/Setup
Classifier: Topic :: System :: Software Distribution
Requires-Python: >=3.6, <4
License-File: LICENSE
License-File: AUTHORS
